pyramid_duh/route.py
pyramid_duh/__init__.py
pyramid_duh/view.py
pyramid_duh/params.py
pyramid_duh/auth.py
pyramid_duh/settings.py
pyramid_duh-0.1.2.dist-info/metadata.json
pyramid_duh-0.1.2.dist-info/RECORD
pyramid_duh-0.1.2.dist-info/WHEEL
pyramid_duh-0.1.2.dist-info/METADATA
pyramid_duh-0.1.2.dist-info/top_level.txt
pyramid_duh-0.1.2.dist-info/DESCRIPTION.rst
