Metadata-Version: 2.0
Name: pyramid-duh
Version: 0.1.2
Summary: Useful utilities for every pyramid app
Home-page: http://pyramid-duh.readthedocs.org/
Author: Steven Arcangeli
Author-email: arcangeli07@gmail.com
License: MIT
Keywords: pyramid util utility
Platform: UNKNOWN
Classifier: Development Status :: 4 - Beta
Classifier: Framework :: Pyramid
Classifier: Intended Audience :: Developers
Classifier: License :: OSI Approved :: MIT License
Classifier: Operating System :: OS Independent
Classifier: Programming Language :: Python
Classifier: Programming Language :: Python :: 2
Classifier: Programming Language :: Python :: 2.6
Classifier: Programming Language :: Python :: 2.7
Classifier: Programming Language :: Python :: 3
Classifier: Programming Language :: Python :: 3.2
Classifier: Programming Language :: Python :: 3.3
Classifier: Topic :: Internet :: WWW/HTTP
Classifier: Topic :: Utilities
Requires-Dist: pyramid
Requires-Dist: six
